odoo/addons/cms_notification/CHANGES.rst
odoo/addons/cms_notification/README.rst
odoo/addons/cms_notification/__init__.py
odoo/addons/cms_notification/__manifest__.py
odoo/addons/cms_notification/controllers/__init__.py
odoo/addons/cms_notification/controllers/main.py
odoo/addons/cms_notification/i18n/cms_notification.pot
odoo/addons/cms_notification/i18n/de.po
odoo/addons/cms_notification/i18n/fr.po
odoo/addons/cms_notification/i18n/hi_IN.po
odoo/addons/cms_notification/images/cms_notif_listing.png
odoo/addons/cms_notification/images/cms_notif_menu.png
odoo/addons/cms_notification/images/cms_notif_settings.png
odoo/addons/cms_notification/models/__init__.py
odoo/addons/cms_notification/models/mail_message.py
odoo/addons/cms_notification/models/mail_message_subtype.py
odoo/addons/cms_notification/models/notification_listing.py
odoo/addons/cms_notification/models/notification_panel_form.py
odoo/addons/cms_notification/models/res_users.py
odoo/addons/cms_notification/models/widget.py
odoo/addons/cms_notification/security/notification_permission.xml
odoo/addons/cms_notification/static/description/icon.png
odoo/addons/cms_notification/static/src/js/read_unread.js
odoo/addons/cms_notification/static/src/less/styles.less
odoo/addons/cms_notification/templates/assets.xml
odoo/addons/cms_notification/templates/help_msg.xml
odoo/addons/cms_notification/templates/notification_listing.xml
odoo/addons/cms_notification/templates/user_menu.xml
odoo/addons/cms_notification/templates/widget.xml
odoo/addons/cms_notification/tests/__init__.py
odoo/addons/cms_notification/tests/fake_models.py
odoo/addons/cms_notification/tests/test_controller.py
odoo/addons/cms_notification/tests/test_mail_message.py
odoo/addons/cms_notification/tests/test_notification_panel_form.py
odoo/addons/cms_notification/tests/test_notification_search_form.py
odoo/addons/cms_notification/tests/test_res_users.py
odoo/addons/cms_notification/tests/test_user_permission.py
odoo11_addon_cms_notification-11.0.1.0.3.dist-info/METADATA
odoo11_addon_cms_notification-11.0.1.0.3.dist-info/RECORD
odoo11_addon_cms_notification-11.0.1.0.3.dist-info/WHEEL
odoo11_addon_cms_notification-11.0.1.0.3.dist-info/top_level.txt
